chromas/README.md
chromas/__init__.py
chromas/chromas.py
chromas/source/__init__.py
"chromas/source/analysis/__init__,py"
chromas/source/analysis/areas_clustering.py
chromas/source/analysis/clustering_utils.py
chromas/source/analysis/ica_slice_clustering.py
chromas/source/analysis/sliceareas_clustering.py
chromas/source/areas/__init__.py
chromas/source/areas/areas.py
chromas/source/chunking/__init__.py
chromas/source/chunking/chunking.py
chromas/source/ica/ica_areas.py
chromas/source/ica/ica_slices.py
chromas/source/ica/ica_utils.py
chromas/source/moving_least_squares/.gitignore
chromas/source/moving_least_squares/pyproject.toml
chromas/source/moving_least_squares/setup.py
chromas/source/moving_least_squares/src/.gitignore
chromas/source/moving_least_squares/src/moving_least_squares.pyx
chromas/source/registration/__init__.py
chromas/source/registration/mls.c
chromas/source/registration/mls.pyx
chromas/source/registration/registration.py
chromas/source/segmentation/__init__.py
chromas/source/segmentation/lookup_utils.py
chromas/source/segmentation/neuralnet_utils.py
chromas/source/segmentation/segmentation_lookup.py
chromas/source/segmentation/segmentation_neuralnet.py
chromas/source/segmentation/segmentation_neuralnet_gpu.py
chromas/source/segmentation/segmentation_randomforest.py
chromas/source/slicing/__init__.py
chromas/source/slicing/generate.py
chromas/source/slicing/interactive_motion_marker_tuner.py
chromas/source/slicing/motion_marker_utils.py
chromas/source/slicing/slicing.py
chromas/source/stitching/image_point_selector.py
chromas/source/stitching/libreg.py
chromas/source/stitching/minimal_removal.py
chromas/source/stitching/stitching.py
chromas/source/superstitching/superstitching.py
chromas/source/tools/generate_segmentation_test_video_letters.py
chromas/source/tools/print_dataset.py
chromas/source/tools/select_chroms.py
chromas/source/tools/status_dataset.py
chromas/source/training/__init__.py
chromas/source/training/neural_net_training.py
chromas-0.1.1.dist-info/LICENSE
chromas-0.1.1.dist-info/METADATA
chromas-0.1.1.dist-info/WHEEL
chromas-0.1.1.dist-info/entry_points.txt
chromas-0.1.1.dist-info/RECORD
