Metadata-Version: 2.3
Name: chromas
Version: 0.1.1
Summary: A tool for the computational analysis of chromatophore activity.
Author: Johann Ukrow
Author-email: johann.ukrow@brain.mpg.de
Requires-Python: >=3.11.0,<4.0.0
Classifier: Programming Language :: Python :: 3
Classifier: Programming Language :: Python :: 3.11
Classifier: Programming Language :: Python :: 3.12
Classifier: Programming Language :: Python :: 3.13
Requires-Dist: albumentations (>=1.4.11,<2.0.0)
Requires-Dist: bokeh (>=3.6.2,<4.0.0)
Requires-Dist: click (>=8.1.7,<9.0.0)
Requires-Dist: cython (>=3.0.11,<4.0.0)
Requires-Dist: dash (>=2.18.0,<3.0.0)
Requires-Dist: dask-jobqueue (>=0.8.5,<0.9.0)
Requires-Dist: dask[distributed] (>=2024.7.0,<2025.0.0)
Requires-Dist: igraph (>=0.11.6,<0.12.0)
Requires-Dist: imageio[ffmpeg] (>=2.35.0,<3.0.0)
Requires-Dist: ipycytoscape (>=1.3.3,<2.0.0)
Requires-Dist: ipykernel (>=6.29.5,<7.0.0)
Requires-Dist: joblib (>=1.4.2,<2.0.0)
Requires-Dist: jupyter-client (>=8.6.2,<9.0.0)
Requires-Dist: kneed (>=0.8.5,<0.9.0)
Requires-Dist: kornia[x] (>=0.7.3,<0.8.0)
Requires-Dist: matplotlib (==3.10.0)
Requires-Dist: nbsphinx (>=0.9.6,<0.10.0)
Requires-Dist: networkx (>=3.4.2,<4.0.0)
Requires-Dist: numpy (>=2.2.2,<3.0.0)
Requires-Dist: opencv-python (>=4.10.0.84,<5.0.0.0)
Requires-Dist: pandoc (>=2.3,<3.0)
Requires-Dist: plotly (>=5.24.0,<6.0.0)
Requires-Dist: pytest (>=8.3.4,<9.0.0)
Requires-Dist: rich (>=13.9.4,<14.0.0)
Requires-Dist: scikit-image (>=0.24.0,<0.25.0)
Requires-Dist: scikit-learn (>=1.5.1,<2.0.0)
Requires-Dist: scipy (>=1.15.1,<2.0.0)
Requires-Dist: sphinx (>=8.1.3,<9.0.0)
Requires-Dist: sphinx-simplepdf (>=1.6.0,<2.0.0)
Requires-Dist: tensorboard (>=2.18.0,<3.0.0)
Requires-Dist: threadpoolctl (>=3.5.0,<4.0.0)
Requires-Dist: tk (>=0.1.0,<0.2.0)
Requires-Dist: torchmetrics (>=1.6.1,<2.0.0)
Requires-Dist: tqdm (>=4.66.4,<5.0.0)
Requires-Dist: trogon (==0.3.0)
Requires-Dist: xarray (>=2024.6.0,<2025.0.0)
Requires-Dist: zarr (>=2.18.2,<3.0.0)
